<metadata xml:lang="nb"><Esri><CreaDate>20210110</CreaDate><CreaTime>00421700</CreaTime><ArcGISFormat>1.0</ArcGISFormat><SyncOnce>TRUE</SyncOnce><ModDate>20210116</ModDate><ModTime>0492300</ModTime><scaleRange><minScale>150000000</minScale><maxScale>5000</maxScale></scaleRange><ArcGISProfile>ItemDescription</ArcGISProfile></Esri><tool name="UpdateMetaId" displayname="Update MetaId" toolboxalias="" xmlns=""><arcToolboxHelpPath>c:\program files (x86)\arcgis\desktop10.7\Help\gp</arcToolboxHelpPath><parameters><param name="pg_version" displayname="Select PostgreSQL version" type="Required" direction="Input" datatype="String" expression="9,6 | 12 | 11 | 10 | 9,5 | 9,4 | 9,3 | 9,2 | 9,1 | 9"><dialogReference>&lt;DIV STYLE="text-align:Left;"&gt;&lt;DIV&gt;&lt;DIV&gt;&lt;P&gt;&lt;SPAN&gt;PostgreSQL version. Velg fra liste (Default: 9.6)&lt;/SPAN&gt;&lt;/P&gt;&lt;/DIV&gt;&lt;/DIV&gt;&lt;/DIV&gt;</dialogReference></param><param name="db_user" displayname="Database user" type="Required" direction="Input" datatype="String" expression="db_user"><dialogReference>&lt;DIV STYLE="text-align:Left;"&gt;&lt;DIV&gt;&lt;DIV&gt;&lt;P&gt;&lt;SPAN&gt;PostgreSQL database brukernavn&lt;/SPAN&gt;&lt;SPAN&gt;. &lt;/SPAN&gt;&lt;SPAN&gt;(&lt;/SPAN&gt;&lt;SPAN&gt;Default: postgres&lt;/SPAN&gt;&lt;SPAN&gt;)&lt;/SPAN&gt;&lt;/P&gt;&lt;/DIV&gt;&lt;/DIV&gt;&lt;/DIV&gt;</dialogReference></param><param name="db_password" displayname="Database password" type="Required" direction="Input" datatype="String Hidden" expression="db_password"><dialogReference>&lt;DIV STYLE="text-align:Left;"&gt;&lt;DIV&gt;&lt;DIV&gt;&lt;P&gt;&lt;SPAN&gt;PostgreSQL database passord &lt;/SPAN&gt;&lt;SPAN&gt;til brukernavnet&lt;/SPAN&gt;&lt;SPAN&gt;.&lt;/SPAN&gt;&lt;/P&gt;&lt;/DIV&gt;&lt;/DIV&gt;&lt;/DIV&gt;</dialogReference></param><param name="db_name" displayname="Database name" type="Required" direction="Input" datatype="String" expression="db_name"><dialogReference>&lt;DIV STYLE="text-align:Left;"&gt;&lt;DIV&gt;&lt;DIV&gt;&lt;P&gt;&lt;SPAN&gt;PostgreSQL database navn. Velg fra liste&lt;/SPAN&gt;&lt;/P&gt;&lt;/DIV&gt;&lt;/DIV&gt;&lt;/DIV&gt;</dialogReference></param><param name="in_excel" displayname="Input Excel" type="Required" direction="Input" datatype="Table" expression="in_excel"><dialogReference>&lt;DIV STYLE="text-align:Left;"&gt;&lt;DIV&gt;&lt;DIV&gt;&lt;P&gt;&lt;SPAN&gt;Input Excel&lt;/SPAN&gt;&lt;SPAN&gt;-&lt;/SPAN&gt;&lt;SPAN&gt;fil som inneholder MetaId'ene som skal oppdaters&lt;/SPAN&gt;&lt;/P&gt;&lt;/DIV&gt;&lt;/DIV&gt;&lt;/DIV&gt;</dialogReference></param><param name="log_folder" displayname="Output Log Folder" type="Required" direction="Input" datatype="Workspace" expression="log_folder"><dialogReference>&lt;DIV STYLE="text-align:Left;"&gt;&lt;DIV&gt;&lt;P&gt;&lt;SPAN&gt;Mappe hvor log filen skal lagres&lt;/SPAN&gt;&lt;/P&gt;&lt;/DIV&gt;&lt;/DIV&gt;</dialogReference></param></parameters><summary>&lt;DIV STYLE="text-align:Left;"&gt;&lt;DIV&gt;&lt;DIV&gt;&lt;P&gt;&lt;SPAN&gt;Update MetaId: Oppdatere MetaId til Class/SubClass/RelationType... i et Intrasis prosjekt basert p책 input tabell.&lt;/SPAN&gt;&lt;/P&gt;&lt;P&gt;&lt;SPAN&gt;Utviklet av &lt;/SPAN&gt;&lt;SPAN STYLE="font-weight:bold;"&gt;Kulturhistorisk museum&lt;/SPAN&gt;&lt;/P&gt;&lt;P&gt;&lt;SPAN&gt;Excel-filen m책 ha disse kolonnene:&lt;/SPAN&gt;&lt;/P&gt;&lt;P&gt;&lt;SPAN STYLE="font-weight:bold;"&gt;MetaId&lt;/SPAN&gt;&lt;SPAN&gt;: for eksisterende MetaId i prosjektet&lt;/SPAN&gt;&lt;/P&gt;&lt;P&gt;&lt;SPAN STYLE="font-weight:bold;"&gt;Name&lt;/SPAN&gt;&lt;SPAN&gt;: for exsisterende Name i prosjektet&lt;/SPAN&gt;&lt;/P&gt;&lt;P&gt;&lt;SPAN STYLE="font-weight:bold;"&gt;New_MetaId&lt;/SPAN&gt;&lt;SPAN&gt;: for ny MetaId som skal erstatte det eksisterende MetaId&lt;/SPAN&gt;&lt;/P&gt;&lt;P&gt;&lt;SPAN STYLE="font-weight:bold;"&gt;New_Name&lt;/SPAN&gt;&lt;SPAN&gt;: for det nye Name som skal erstatte det eksisterende Name&lt;/SPAN&gt;&lt;/P&gt;&lt;P&gt;&lt;SPAN STYLE="font-weight:bold;"&gt;SubClass_ClassId&lt;/SPAN&gt;&lt;SPAN&gt;: for ClassId til SubClass type&lt;/SPAN&gt;&lt;/P&gt;&lt;P&gt;&lt;SPAN STYLE="font-weight:bold;"&gt;Type&lt;/SPAN&gt;&lt;SPAN&gt;: for Type Class, SubClass, RelationType&lt;/SPAN&gt;&lt;/P&gt;&lt;P&gt;&lt;SPAN /&gt;&lt;/P&gt;&lt;/DIV&gt;&lt;/DIV&gt;&lt;/DIV&gt;</summary></tool><dataIdInfo><idCitation><resTitle>Update MetaId</resTitle></idCitation><idAbs>&lt;DIV STYLE="text-align:Left;"&gt;&lt;DIV&gt;&lt;DIV&gt;&lt;P&gt;&lt;SPAN&gt;Update MetaId: Oppdatere MetaId til Class/SubClass/RelationType... i et Intrasis prosjekt basert p책 input tabell.&lt;/SPAN&gt;&lt;/P&gt;&lt;P&gt;&lt;SPAN&gt;Utviklet av &lt;/SPAN&gt;&lt;SPAN STYLE="font-weight:bold;"&gt;Kulturhistorisk museum&lt;/SPAN&gt;&lt;/P&gt;&lt;P&gt;&lt;SPAN&gt;Excel-filen m책 ha disse kolonnene:&lt;/SPAN&gt;&lt;/P&gt;&lt;P&gt;&lt;SPAN STYLE="font-weight:bold;"&gt;MetaId&lt;/SPAN&gt;&lt;SPAN&gt;: for eksisterende MetaId i prosjektet&lt;/SPAN&gt;&lt;/P&gt;&lt;P&gt;&lt;SPAN STYLE="font-weight:bold;"&gt;Name&lt;/SPAN&gt;&lt;SPAN&gt;: for exsisterende Name i prosjektet&lt;/SPAN&gt;&lt;/P&gt;&lt;P&gt;&lt;SPAN STYLE="font-weight:bold;"&gt;New_MetaId&lt;/SPAN&gt;&lt;SPAN&gt;: for ny MetaId som skal erstatte det eksisterende MetaId&lt;/SPAN&gt;&lt;/P&gt;&lt;P&gt;&lt;SPAN STYLE="font-weight:bold;"&gt;New_Name&lt;/SPAN&gt;&lt;SPAN&gt;: for det nye Name som skal erstatte det eksisterende Name&lt;/SPAN&gt;&lt;/P&gt;&lt;P&gt;&lt;SPAN STYLE="font-weight:bold;"&gt;SubClass_ClassId&lt;/SPAN&gt;&lt;SPAN&gt;: for ClassId til SubClass type&lt;/SPAN&gt;&lt;/P&gt;&lt;P&gt;&lt;SPAN STYLE="font-weight:bold;"&gt;Type&lt;/SPAN&gt;&lt;SPAN&gt;: for Type Class, SubClass, RelationType&lt;/SPAN&gt;&lt;/P&gt;&lt;P&gt;&lt;SPAN /&gt;&lt;/P&gt;&lt;/DIV&gt;&lt;/DIV&gt;&lt;/DIV&gt;</idAbs><searchKeys><keyword>Intrasis</keyword></searchKeys><idCredit>Kulturhistorisk museum</idCredit></dataIdInfo><distInfo><distributor><distorFormat><formatName>ArcToolbox Tool</formatName></distorFormat></distributor></distInfo><mdHrLv><ScopeCd value="005"/></mdHrLv></metadata>
